{"regressions": [["basic_functions.BasicFunctions.time_read_short_wide(1000000)", "graphs/branch-master/machine-ArcticDB-Medium-Runner/python-3.6/version-null/basic_functions.BasicFunctions.time_read_short_wide.json", {"python": "3.6"}, 0, 1.107307655200111, 0.9466348452000602, [[1914, 2355, 0.9466348452000602, 1.107307655200111]]], ["basic_functions.BasicFunctions.time_read_short_wide(1500000)", "graphs/branch-master/machine-ArcticDB-Medium-Runner/python-3.6/version-null/basic_functions.BasicFunctions.time_read_short_wide.json", {"python": "3.6"}, 1, 1.104668499599984, 0.9426164956999855, [[1914, 2355, 0.9426164956999855, 1.104668499599984]]], ["version_chain.IterateVersionChain.time_read_alternating(25000, 'forever', 0.0)", "graphs/branch-master/machine-ArcticDB-Medium-Runner/python-3.6/version-null/version_chain.IterateVersionChain.time_read_alternating.json", {"python": "3.6"}, 0, 0.35407350855000463, 0.002973967999969318, [[3201, 3226, 0.002973967999969318, 0.35407350855000463]]], ["version_chain.IterateVersionChain.time_read_alternating(25000, 'forever', 0.99)", "graphs/branch-master/machine-ArcticDB-Medium-Runner/python-3.6/version-null/version_chain.IterateVersionChain.time_read_alternating.json", {"python": "3.6"}, 1, 0.007791241700033424, 0.0005211187499980952, [[3201, 3226, 0.0005211187499980952, 0.007791241700033424]]], ["version_chain.IterateVersionChain.time_read_v0(25000, 'forever', 0.0)", "graphs/branch-master/machine-ArcticDB-Medium-Runner/python-3.6/version-null/version_chain.IterateVersionChain.time_read_v0.json", {"python": "3.6"}, 0, 0.000262833499982662, 0.00023479065000628905, [[null, 3848, 0.00023479065000628905, 0.000262833499982662]]], ["version_chain.IterateVersionChain.time_load_all_versions(25000, 'forever', 0.0)", "graphs/branch-master/machine-ArcticDB-Medium-Runner/python-3.6/version-null/version_chain.IterateVersionChain.time_load_all_versions.json", {"python": "3.6"}, 0, 0.000280687200029206, 0.0002334718999463803, [[3857, 3867, 0.0002334718999463803, 0.000280687200029206]]], ["version_chain.IterateVersionChain.time_load_all_versions(25000, 'default', 0.0)", "graphs/branch-master/machine-ArcticDB-Medium-Runner/python-3.6/version-null/version_chain.IterateVersionChain.time_load_all_versions.json", {"python": "3.6"}, 2, 0.00027545499997359, 0.00023465439996925853, [[3857, 3867, 0.00023465439996925853, 0.00027545499997359]]], ["resample.Resample.time_resample(1000000, 100, 'int', 'mean')", "graphs/branch-master/machine-ArcticDB-Medium-Runner/python-3.6/version-null/resample.Resample.time_resample.json", {"python": "3.6"}, 43, 0.004198532300051738, 0.0039526266999928335, [[null, 3730, 0.0039526266999928335, 0.004198532300051738]]], ["resample.Resample.peakmem_resample(10000000, 100, 'bool', 'last')", "graphs/branch-master/machine-ArcticDB-Medium-Runner/python-3.6/version-null/resample.Resample.peakmem_resample.json", {"python": "3.6"}, 145, 189581312.0, 180494336.0, [[null, 3963, 180494336.0, 189581312.0]]], ["resample.Resample.peakmem_resample(10000000, 100, 'int', 'min')", "graphs/branch-master/machine-ArcticDB-Medium-Runner/python-3.6/version-null/resample.Resample.peakmem_resample.json", {"python": "3.6"}, 149, 261836800.0, 247566336.0, [[3857, 3867, 247566336.0, 261836800.0]]], ["resample.Resample.peakmem_resample(10000000, 100, 'int', 'max')", "graphs/branch-master/machine-ArcticDB-Medium-Runner/python-3.6/version-null/resample.Resample.peakmem_resample.json", {"python": "3.6"}, 150, 263143424.0, 249786368.0, [[3857, 3867, 249786368.0, 263143424.0]]], ["resample.Resample.peakmem_resample(10000000, 100, 'int', 'last')", "graphs/branch-master/machine-ArcticDB-Medium-Runner/python-3.6/version-null/resample.Resample.peakmem_resample.json", {"python": "3.6"}, 152, 262137856.0, 248938496.0, [[3857, 3867, 248938496.0, 262137856.0]]], ["resample.Resample.peakmem_resample(10000000, 100, 'float', 'mean')", "graphs/branch-master/machine-ArcticDB-Medium-Runner/python-3.6/version-null/resample.Resample.peakmem_resample.json", {"python": "3.6"}, 155, 301484032.0, 285171712.0, [[3857, 3867, 285171712.0, 301484032.0]]], ["resample.Resample.peakmem_resample(10000000, 100, 'float', 'first')", "graphs/branch-master/machine-ArcticDB-Medium-Runner/python-3.6/version-null/resample.Resample.peakmem_resample.json", {"python": "3.6"}, 158, 299429888.0, 282943488.0, [[3857, 3867, 282943488.0, 299429888.0]]], ["resample.Resample.peakmem_resample(10000000, 100, 'float', 'last')", "graphs/branch-master/machine-ArcticDB-Medium-Runner/python-3.6/version-null/resample.Resample.peakmem_resample.json", {"python": "3.6"}, 159, 300789760.0, 286377984.0, [[null, 3869, 286377984.0, 300789760.0]]], ["resample.Resample.peakmem_resample(10000000, 100, 'float', 'count')", "graphs/branch-master/machine-ArcticDB-Medium-Runner/python-3.6/version-null/resample.Resample.peakmem_resample.json", {"python": "3.6"}, 160, 299442176.0, 282404864.0, [[null, 3857, 282404864.0, 299442176.0]]], ["resample.Resample.peakmem_resample(10000000, 100, 'datetime', 'mean')", "graphs/branch-master/machine-ArcticDB-Medium-Runner/python-3.6/version-null/resample.Resample.peakmem_resample.json", {"python": "3.6"}, 162, 299640832.0, 285368320.0, [[3857, 3867, 285368320.0, 299640832.0]]], ["resample.Resample.peakmem_resample(10000000, 100, 'datetime', 'first')", "graphs/branch-master/machine-ArcticDB-Medium-Runner/python-3.6/version-null/resample.Resample.peakmem_resample.json", {"python": "3.6"}, 165, 299761664.0, 281608192.0, [[3857, 3867, 281608192.0, 299761664.0]]], ["resample.Resample.peakmem_resample(10000000, 100000, 'int', 'sum')", "graphs/branch-master/machine-ArcticDB-Medium-Runner/python-3.6/version-null/resample.Resample.peakmem_resample.json", {"python": "3.6"}, 182, 260915200.0, 247476224.0, [[3857, 3867, 247476224.0, 260915200.0]]], ["resample.Resample.peakmem_resample(10000000, 100000, 'int', 'mean')", "graphs/branch-master/machine-ArcticDB-Medium-Runner/python-3.6/version-null/resample.Resample.peakmem_resample.json", {"python": "3.6"}, 183, 262492160.0, 248064000.0, [[null, 3869, 248064000.0, 262492160.0]]], ["resample.Resample.peakmem_resample(10000000, 100000, 'int', 'min')", "graphs/branch-master/machine-ArcticDB-Medium-Runner/python-3.6/version-null/resample.Resample.peakmem_resample.json", {"python": "3.6"}, 184, 263464960.0, 246960128.0, [[3857, 3867, 246960128.0, 263464960.0]]], ["resample.Resample.peakmem_resample(10000000, 100000, 'int', 'first')", "graphs/branch-master/machine-ArcticDB-Medium-Runner/python-3.6/version-null/resample.Resample.peakmem_resample.json", {"python": "3.6"}, 186, 262021120.0, 248066048.0, [[null, 3869, 248066048.0, 262021120.0]]], ["resample.Resample.peakmem_resample(10000000, 100000, 'float', 'sum')", "graphs/branch-master/machine-ArcticDB-Medium-Runner/python-3.6/version-null/resample.Resample.peakmem_resample.json", {"python": "3.6"}, 189, 298242048.0, 283996160.0, [[3857, 3867, 283996160.0, 298242048.0]]], ["resample.Resample.peakmem_resample(10000000, 100000, 'float', 'first')", "graphs/branch-master/machine-ArcticDB-Medium-Runner/python-3.6/version-null/resample.Resample.peakmem_resample.json", {"python": "3.6"}, 193, 300179456.0, 283058176.0, [[null, 3869, 283058176.0, 300179456.0]]], ["resample.Resample.peakmem_resample(10000000, 100000, 'float', 'last')", "graphs/branch-master/machine-ArcticDB-Medium-Runner/python-3.6/version-null/resample.Resample.peakmem_resample.json", {"python": "3.6"}, 194, 299110400.0, 279527424.0, [[null, 3869, 279527424.0, 299110400.0]]], ["resample.Resample.peakmem_resample(10000000, 100000, 'datetime', 'min')", "graphs/branch-master/machine-ArcticDB-Medium-Runner/python-3.6/version-null/resample.Resample.peakmem_resample.json", {"python": "3.6"}, 198, 299036672.0, 283740160.0, [[null, 3857, 283740160.0, 299036672.0]]], ["resample.Resample.peakmem_resample(10000000, 100000, 'datetime', 'first')", "graphs/branch-master/machine-ArcticDB-Medium-Runner/python-3.6/version-null/resample.Resample.peakmem_resample.json", {"python": "3.6"}, 200, 297431040.0, 281262080.0, [[null, 3869, 281262080.0, 297431040.0]]], ["resample.Resample.peakmem_resample(10000000, 100000, 'datetime', 'count')", "graphs/branch-master/machine-ArcticDB-Medium-Runner/python-3.6/version-null/resample.Resample.peakmem_resample.json", {"python": "3.6"}, 202, 298186752.0, 283340800.0, [[3857, 3867, 283340800.0, 298186752.0]]], ["resample.Resample.peakmem_resample(10000000, 100000, 'str', 'first')", "graphs/branch-master/machine-ArcticDB-Medium-Runner/python-3.6/version-null/resample.Resample.peakmem_resample.json", {"python": "3.6"}, 207, 253784064.0, 241680384.0, [[null, 3869, 241680384.0, 253784064.0]]], ["basic_functions.BatchBasicFunctions.time_write_batch(25000, 500)", "graphs/branch-master/machine-ArcticDB-Medium-Runner/python-3.6/version-null/basic_functions.BatchBasicFunctions.time_write_batch.json", {"python": "3.6"}, 0, 8.013437566999983, 7.168476821299965, [[null, 3848, 7.221718522100036, 8.013437566999983]]], ["basic_functions.BatchBasicFunctions.time_write_batch(25000, 1000)", "graphs/branch-master/machine-ArcticDB-Medium-Runner/python-3.6/version-null/basic_functions.BatchBasicFunctions.time_write_batch.json", {"python": "3.6"}, 1, 16.020967660899984, 14.270519084999954, [[null, 3848, 14.51427073139996, 16.020967660899984]]], ["basic_functions.BatchBasicFunctions.time_write_batch(50000, 500)", "graphs/branch-master/machine-ArcticDB-Medium-Runner/python-3.6/version-null/basic_functions.BatchBasicFunctions.time_write_batch.json", {"python": "3.6"}, 2, 8.277313936699965, 7.38612087409997, [[null, 3848, 7.38612087409997, 8.277313936699965]]], ["basic_functions.BatchBasicFunctions.time_write_batch(50000, 1000)", "graphs/branch-master/machine-ArcticDB-Medium-Runner/python-3.6/version-null/basic_functions.BatchBasicFunctions.time_write_batch.json", {"python": "3.6"}, 3, 16.52994032059992, 15.109564549000016, [[null, 3848, 15.109564549000016, 16.52994032059992]]], ["version_chain.IterateVersionChain.time_read_from_epoch(25000, 'forever', 0.0)", "graphs/branch-master/machine-ArcticDB-Medium-Runner/python-3.6/version-null/version_chain.IterateVersionChain.time_read_from_epoch.json", {"python": "3.6"}, 0, 0.3503859081499968, 0.002762416850009686, [[3201, 3226, 0.002762416850009686, 0.3503859081499968]]], ["version_chain.IterateVersionChain.time_read_from_epoch(25000, 'forever', 0.99)", "graphs/branch-master/machine-ArcticDB-Medium-Runner/python-3.6/version-null/version_chain.IterateVersionChain.time_read_from_epoch.json", {"python": "3.6"}, 1, 0.004170369250050499, 0.0003276425000194649, [[3201, 3226, 0.0003276425000194649, 0.004170369250050499]]], ["basic_functions.BasicFunctions.time_write(1000000)", "graphs/branch-master/machine-ArcticDB-Medium-Runner/python-3.6/version-null/basic_functions.BasicFunctions.time_write.json", {"python": "3.6"}, 0, 0.09365834400005041, 0.07092043019997618, [[3667, 3676, 0.07092043019997618, 0.0800872181000159], [null, 3857, 0.0800872181000159, 0.09365834400005041]]], ["basic_functions.BasicFunctions.time_write(1500000)", "graphs/branch-master/machine-ArcticDB-Medium-Runner/python-3.6/version-null/basic_functions.BasicFunctions.time_write.json", {"python": "3.6"}, 1, 0.13335874769995826, 0.11336860480002997, [[null, 3848, 0.11336860480002997, 0.13335874769995826]]], ["basic_functions.ModificationFunctions.time_update_single(1000000)", "graphs/branch-master/machine-ArcticDB-Medium-Runner/python-3.6/version-null/basic_functions.ModificationFunctions.time_update_single.json", {"python": "3.6"}, 0, 0.04609095699925092, 0.032875244000024395, [[4036, 4044, 0.032875244000024395, 0.04609095699925092]]], ["basic_functions.ModificationFunctions.time_update_single(1500000)", "graphs/branch-master/machine-ArcticDB-Medium-Runner/python-3.6/version-null/basic_functions.ModificationFunctions.time_update_single.json", {"python": "3.6"}, 1, 0.05973351800093951, 0.05161792199942283, [[4036, 4044, 0.05161792199942283, 0.05973351800093951]]], ["basic_functions.ModificationFunctions.time_delete(1000000)", "graphs/branch-master/machine-ArcticDB-Medium-Runner/python-3.6/version-null/basic_functions.ModificationFunctions.time_delete.json", {"python": "3.6"}, 0, 0.037092386999574956, 0.024765262998698745, [[4036, 4044, 0.024765262998698745, 0.037092386999574956]]], ["basic_functions.ModificationFunctions.time_update_upsert(1000000)", "graphs/branch-master/machine-ArcticDB-Medium-Runner/python-3.6/version-null/basic_functions.ModificationFunctions.time_update_upsert.json", {"python": "3.6"}, 0, 0.11927706500136992, 0.11344627099970239, [[4036, 4044, 0.11344627099970239, 0.11927706500136992]]], ["basic_functions.ModificationFunctions.time_update_half(1000000)", "graphs/branch-master/machine-ArcticDB-Medium-Runner/python-3.6/version-null/basic_functions.ModificationFunctions.time_update_half.json", {"python": "3.6"}, 0, 0.08987694700044813, 0.08354870599941933, [[4036, 4044, 0.08354870599941933, 0.08987694700044813]]], ["basic_functions.ModificationFunctions.time_update_half(1500000)", "graphs/branch-master/machine-ArcticDB-Medium-Runner/python-3.6/version-null/basic_functions.ModificationFunctions.time_update_half.json", {"python": "3.6"}, 1, 0.12425244700170879, 0.11186359499879472, [[4036, 4044, 0.11186359499879472, 0.12425244700170879]]], ["basic_functions.ModificationFunctions.time_append_single(1000000)", "graphs/branch-master/machine-ArcticDB-Medium-Runner/python-3.6/version-null/basic_functions.ModificationFunctions.time_append_single.json", {"python": "3.6"}, 0, 0.03853251799955615, 0.033073262000471004, [[4036, 4044, 0.033073262000471004, 0.03853251799955615]]], ["basic_functions.ModificationFunctions.time_append_single(1500000)", "graphs/branch-master/machine-ArcticDB-Medium-Runner/python-3.6/version-null/basic_functions.ModificationFunctions.time_append_single.json", {"python": "3.6"}, 1, 0.04574739200143085, 0.037387152999144746, [[4036, 4044, 0.037387152999144746, 0.04574739200143085]]]]}