{
  "$schema": "https://raw.githubusercontent.com/spdx/spdx-spec/v2.2.1/schemas/spdx-schema.json",
  "spdxVersion": "SPDX-2.2",
  "dataLicense": "CC0-1.0",
  "SPDXID": "SPDXRef-DOCUMENT",
  "documentNamespace": "https://spdx.org/spdxdocs/boost-exception-x64-linux-1.80.0#1-f2706790-67f0-4b0f-8119-fe7738b0a36c",
  "name": "boost-exception:x64-linux@1.80.0#1 1ac0e8199b98162d174c3ddf8eda975d60c86a919591c84340b9b0b5ef0ae101",
  "creationInfo": {
    "creators": [
      "Tool: vcpkg-ac02a9f660977426b8ec6392919fbb1d51b10998"
    ],
    "created": "2023-12-08T10:10:17Z"
  },
  "relationships": [
    {
      "spdxElementId": "SPDXRef-port",
      "relationshipType": "GENERATES",
      "relatedSpdxElement": "SPDXRef-binary"
    },
    {
      "spdxElementId": "SPDXRef-port",
      "relationshipType": "CONTAINS",
      "relatedSpdxElement": "SPDXRef-file-0"
    },
    {
      "spdxElementId": "SPDXRef-port",
      "relationshipType": "CONTAINS",
      "relatedSpdxElement": "SPDXRef-file-1"
    },
    {
      "spdxElementId": "SPDXRef-binary",
      "relationshipType": "GENERATED_FROM",
      "relatedSpdxElement": "SPDXRef-port"
    },
    {
      "spdxElementId": "SPDXRef-file-0",
      "relationshipType": "CONTAINED_BY",
      "relatedSpdxElement": "SPDXRef-port"
    },
    {
      "spdxElementId": "SPDXRef-file-1",
      "relationshipType": "CONTAINED_BY",
      "relatedSpdxElement": "SPDXRef-port"
    }
  ],
  "packages": [
    {
      "name": "boost-exception",
      "SPDXID": "SPDXRef-port",
      "versionInfo": "1.80.0#1",
      "downloadLocation": "git+https://github.com/Microsoft/vcpkg@bd131b74e6a6bf14aaf31aef22be644b4fa57a3a",
      "homepage": "https://github.com/boostorg/exception",
      "licenseConcluded": "BSL-1.0",
      "licenseDeclared": "NOASSERTION",
      "copyrightText": "NOASSERTION",
      "description": "Boost exception module",
      "comment": "This is the port (recipe) consumed by vcpkg."
    },
    {
      "name": "boost-exception:x64-linux",
      "SPDXID": "SPDXRef-binary",
      "versionInfo": "1ac0e8199b98162d174c3ddf8eda975d60c86a919591c84340b9b0b5ef0ae101",
      "downloadLocation": "NONE",
      "licenseConcluded": "BSL-1.0",
      "licenseDeclared": "NOASSERTION",
      "copyrightText": "NOASSERTION",
      "comment": "This is a binary package built by vcpkg."
    },
    {
      "SPDXID": "SPDXRef-resource-1",
      "name": "boostorg/exception",
      "downloadLocation": "git+https://github.com/boostorg/exception@boost-1.80.0",
      "licenseConcluded": "NOASSERTION",
      "licenseDeclared": "NOASSERTION",
      "copyrightText": "NOASSERTION",
      "checksums": [
        {
          "algorithm": "SHA512",
          "checksumValue": "57477329a2671147db24a6fd9792f8694943c92475d03daab2284c1ca316fca9675ba3a9e6f0adcd5e7361d35869240efff10d373e30c79ba99cb9a4640e649a"
        }
      ]
    }
  ],
  "files": [
    {
      "fileName": ".//home/gpetrov/source/ArcticDB/cpp/vcpkg/buildtrees/versioning_/versions/boost-exception/bd131b74e6a6bf14aaf31aef22be644b4fa57a3a/portfile.cmake",
      "SPDXID": "SPDXRef-file-0",
      "checksums": [
        {
          "algorithm": "SHA256",
          "checksumValue": "410a3cc6bb29ef606fab8039acc50d4df231f4c8910a0107b51102deb4297c7c"
        }
      ],
      "licenseConcluded": "NOASSERTION",
      "copyrightText": "NOASSERTION"
    },
    {
      "fileName": ".//home/gpetrov/source/ArcticDB/cpp/vcpkg/buildtrees/versioning_/versions/boost-exception/bd131b74e6a6bf14aaf31aef22be644b4fa57a3a/vcpkg.json",
      "SPDXID": "SPDXRef-file-1",
      "checksums": [
        {
          "algorithm": "SHA256",
          "checksumValue": "94ed3a148b6954982821ed8d1f3e7aec2fcee1c0d486c5fe1d97274c6f7c032c"
        }
      ],
      "licenseConcluded": "NOASSERTION",
      "copyrightText": "NOASSERTION"
    }
  ]
}
