{
  "$schema": "https://raw.githubusercontent.com/spdx/spdx-spec/v2.2.1/schemas/spdx-schema.json",
  "spdxVersion": "SPDX-2.2",
  "dataLicense": "CC0-1.0",
  "SPDXID": "SPDXRef-DOCUMENT",
  "documentNamespace": "https://spdx.org/spdxdocs/civetweb-x64-linux-1.15#2-607fd98d-ff04-49cd-aca5-02e0b5eb2b49",
  "name": "civetweb:x64-linux@1.15#2 ba291457ac6b0e424f1f5cd5fc39dd9c13c9c354b90ee529c9c51e1b73e45dfc",
  "creationInfo": {
    "creators": [
      "Tool: vcpkg-ac02a9f660977426b8ec6392919fbb1d51b10998"
    ],
    "created": "2023-12-08T10:29:43Z"
  },
  "relationships": [
    {
      "spdxElementId": "SPDXRef-port",
      "relationshipType": "GENERATES",
      "relatedSpdxElement": "SPDXRef-binary"
    },
    {
      "spdxElementId": "SPDXRef-port",
      "relationshipType": "CONTAINS",
      "relatedSpdxElement": "SPDXRef-file-0"
    },
    {
      "spdxElementId": "SPDXRef-port",
      "relationshipType": "CONTAINS",
      "relatedSpdxElement": "SPDXRef-file-1"
    },
    {
      "spdxElementId": "SPDXRef-port",
      "relationshipType": "CONTAINS",
      "relatedSpdxElement": "SPDXRef-file-2"
    },
    {
      "spdxElementId": "SPDXRef-binary",
      "relationshipType": "GENERATED_FROM",
      "relatedSpdxElement": "SPDXRef-port"
    },
    {
      "spdxElementId": "SPDXRef-file-0",
      "relationshipType": "CONTAINED_BY",
      "relatedSpdxElement": "SPDXRef-port"
    },
    {
      "spdxElementId": "SPDXRef-file-1",
      "relationshipType": "CONTAINED_BY",
      "relatedSpdxElement": "SPDXRef-port"
    },
    {
      "spdxElementId": "SPDXRef-file-2",
      "relationshipType": "CONTAINED_BY",
      "relatedSpdxElement": "SPDXRef-port"
    }
  ],
  "packages": [
    {
      "name": "civetweb",
      "SPDXID": "SPDXRef-port",
      "versionInfo": "1.15#2",
      "downloadLocation": "git+https://github.com/Microsoft/vcpkg@f5c4ed510288187d465737a301891b1101d6c373",
      "homepage": "https://github.com/civetweb/civetweb",
      "licenseConcluded": "NOASSERTION",
      "licenseDeclared": "NOASSERTION",
      "copyrightText": "NOASSERTION",
      "description": "Easy to use, powerful, C/C++ embeddable web server.",
      "comment": "This is the port (recipe) consumed by vcpkg."
    },
    {
      "name": "civetweb:x64-linux",
      "SPDXID": "SPDXRef-binary",
      "versionInfo": "ba291457ac6b0e424f1f5cd5fc39dd9c13c9c354b90ee529c9c51e1b73e45dfc",
      "downloadLocation": "NONE",
      "licenseConcluded": "NOASSERTION",
      "licenseDeclared": "NOASSERTION",
      "copyrightText": "NOASSERTION",
      "comment": "This is a binary package built by vcpkg."
    },
    {
      "SPDXID": "SPDXRef-resource-1",
      "name": "civetweb/civetweb",
      "downloadLocation": "git+https://github.com/civetweb/civetweb@eefb26f82b233268fc98577d265352720d477ba4",
      "licenseConcluded": "NOASSERTION",
      "licenseDeclared": "NOASSERTION",
      "copyrightText": "NOASSERTION",
      "checksums": [
        {
          "algorithm": "SHA512",
          "checksumValue": "5ce962e31b3c07b7110cbc645458dba9c0e26e693fbe3b4a7ffe8a28563827049a22fc5596a911fbcea4d88a9adbef3f82000ff61027ff4387f40e4a4045c26d"
        }
      ]
    }
  ],
  "files": [
    {
      "fileName": ".//home/gpetrov/source/ArcticDB/cpp/vcpkg/buildtrees/versioning_/versions/civetweb/f5c4ed510288187d465737a301891b1101d6c373/portfile.cmake",
      "SPDXID": "SPDXRef-file-0",
      "checksums": [
        {
          "algorithm": "SHA256",
          "checksumValue": "fc4eeefbaa1ea61d9825312057dd1460053da43651c3c266cc57208f8a83862e"
        }
      ],
      "licenseConcluded": "NOASSERTION",
      "copyrightText": "NOASSERTION"
    },
    {
      "fileName": ".//home/gpetrov/source/ArcticDB/cpp/vcpkg/buildtrees/versioning_/versions/civetweb/f5c4ed510288187d465737a301891b1101d6c373/vcpkg.json",
      "SPDXID": "SPDXRef-file-1",
      "checksums": [
        {
          "algorithm": "SHA256",
          "checksumValue": "a3375b97735715d8a95209e0a139808963f234f21c23194ad9f9d45bcdf78808"
        }
      ],
      "licenseConcluded": "NOASSERTION",
      "copyrightText": "NOASSERTION"
    },
    {
      "fileName": ".//home/gpetrov/source/ArcticDB/cpp/vcpkg/buildtrees/versioning_/versions/civetweb/f5c4ed510288187d465737a301891b1101d6c373/disable_warnings.patch",
      "SPDXID": "SPDXRef-file-2",
      "checksums": [
        {
          "algorithm": "SHA256",
          "checksumValue": "cc78cb1b33c6a074c1d7c87bdefb74fe2aab0620ac5b48fba66256bfbb356c58"
        }
      ],
      "licenseConcluded": "NOASSERTION",
      "copyrightText": "NOASSERTION"
    }
  ]
}
