{
  "$schema": "https://raw.githubusercontent.com/spdx/spdx-spec/v2.2.1/schemas/spdx-schema.json",
  "spdxVersion": "SPDX-2.2",
  "dataLicense": "CC0-1.0",
  "SPDXID": "SPDXRef-DOCUMENT",
  "documentNamespace": "https://spdx.org/spdxdocs/boost-dynamic-bitset-x64-linux-1.84.0-1037214e-7160-4dd3-8d1b-d8291d79c4f2",
  "name": "boost-dynamic-bitset:x64-linux@1.84.0 ad7e3466c60d9debaba2a87d1ef04676aa7e020ce55b7a38bd98c3065a031219",
  "creationInfo": {
    "creators": [
      "Tool: vcpkg-2024-12-09-1005b78fa1bf1dde1a20c2734cba4ea61ca94d9a"
    ],
    "created": "2025-01-13T11:12:38Z"
  },
  "relationships": [
    {
      "spdxElementId": "SPDXRef-port",
      "relationshipType": "GENERATES",
      "relatedSpdxElement": "SPDXRef-binary"
    },
    {
      "spdxElementId": "SPDXRef-port",
      "relationshipType": "CONTAINS",
      "relatedSpdxElement": "SPDXRef-file-0"
    },
    {
      "spdxElementId": "SPDXRef-port",
      "relationshipType": "CONTAINS",
      "relatedSpdxElement": "SPDXRef-file-1"
    },
    {
      "spdxElementId": "SPDXRef-binary",
      "relationshipType": "GENERATED_FROM",
      "relatedSpdxElement": "SPDXRef-port"
    },
    {
      "spdxElementId": "SPDXRef-file-0",
      "relationshipType": "CONTAINED_BY",
      "relatedSpdxElement": "SPDXRef-port"
    },
    {
      "spdxElementId": "SPDXRef-file-1",
      "relationshipType": "CONTAINED_BY",
      "relatedSpdxElement": "SPDXRef-port"
    }
  ],
  "packages": [
    {
      "name": "boost-dynamic-bitset",
      "SPDXID": "SPDXRef-port",
      "versionInfo": "1.84.0",
      "downloadLocation": "git+https://github.com/Microsoft/vcpkg@9b8fa2fe1a46c7f77f890f83eb124e2f62d21594",
      "homepage": "https://github.com/boostorg/dynamic_bitset",
      "licenseConcluded": "BSL-1.0",
      "licenseDeclared": "NOASSERTION",
      "copyrightText": "NOASSERTION",
      "description": "Boost dynamic_bitset module",
      "comment": "This is the port (recipe) consumed by vcpkg."
    },
    {
      "name": "boost-dynamic-bitset:x64-linux",
      "SPDXID": "SPDXRef-binary",
      "versionInfo": "ad7e3466c60d9debaba2a87d1ef04676aa7e020ce55b7a38bd98c3065a031219",
      "downloadLocation": "NONE",
      "licenseConcluded": "BSL-1.0",
      "licenseDeclared": "NOASSERTION",
      "copyrightText": "NOASSERTION",
      "comment": "This is a binary package built by vcpkg."
    },
    {
      "SPDXID": "SPDXRef-resource-0",
      "name": "boostorg/dynamic_bitset",
      "downloadLocation": "git+https://github.com/boostorg/dynamic_bitset@boost-1.84.0",
      "licenseConcluded": "NOASSERTION",
      "licenseDeclared": "NOASSERTION",
      "copyrightText": "NOASSERTION",
      "checksums": [
        {
          "algorithm": "SHA512",
          "checksumValue": "76229a33e6e659fd0ae0d32f34df0c793da203830f58c3e0a89ec4eeaf5aba4bacbc516ade9860005f74907e42ddb1995a82459e528bd7d3f42fd08c49abb63a"
        }
      ]
    }
  ],
  "files": [
    {
      "fileName": ".//opt/arcticdb/arcticdb_link/cpp/vcpkg/buildtrees/versioning_/versions/boost-dynamic-bitset/9b8fa2fe1a46c7f77f890f83eb124e2f62d21594/portfile.cmake",
      "SPDXID": "SPDXRef-file-0",
      "checksums": [
        {
          "algorithm": "SHA256",
          "checksumValue": "ca7bb73f16fe0cfc548cfa582484df672096128ed9a70063315853296604ea5b"
        }
      ],
      "licenseConcluded": "NOASSERTION",
      "copyrightText": "NOASSERTION"
    },
    {
      "fileName": ".//opt/arcticdb/arcticdb_link/cpp/vcpkg/buildtrees/versioning_/versions/boost-dynamic-bitset/9b8fa2fe1a46c7f77f890f83eb124e2f62d21594/vcpkg.json",
      "SPDXID": "SPDXRef-file-1",
      "checksums": [
        {
          "algorithm": "SHA256",
          "checksumValue": "20a495381f5e887edfcebd515731a272574be0d19c531f0cdeb5b7a4882f185d"
        }
      ],
      "licenseConcluded": "NOASSERTION",
      "copyrightText": "NOASSERTION"
    }
  ]
}
